xarray_fancy_repr/__init__.py
xarray_fancy_repr/utils.py
xarray_fancy_repr/widget.py
xarray_fancy_repr/wrap.py
xarray_fancy_repr/static/widget.css
xarray_fancy_repr/static/widget.js
xarray_fancy_repr-0.0.2.dist-info/METADATA
xarray_fancy_repr-0.0.2.dist-info/WHEEL
xarray_fancy_repr-0.0.2.dist-info/licenses/LICENSE
xarray_fancy_repr-0.0.2.dist-info/RECORD
