Metadata-Version: 2.1
Name: xarray-fancy-repr
Version: 0.0.2
Summary: Fancy reprs for Xarray objects in Jupyter notebooks
Project-URL: Repository, https://github.com/benbovy/xarray-fancy-repr
Author: Benoît Bovy
Maintainer: xarray-fancy-repr contributors
License: Apache-2.0
License-File: LICENSE
Keywords: jupyter,widget,xarray
Requires-Dist: anywidget
Requires-Dist: xarray
Provides-Extra: dev
Requires-Dist: jupyterlab; extra == 'dev'
Requires-Dist: pre-commit; extra == 'dev'
Requires-Dist: pytest; extra == 'dev'
Requires-Dist: watchfiles; extra == 'dev'
